snakestream/__init__.py
snakestream/base_stream.py
snakestream/collector.py
snakestream/exception.py
snakestream/parallel_stream.py
snakestream/sort.py
snakestream/stream.py
snakestream/stream_builder.py
snakestream/type.py
snakestream-0.3.5.dist-info/LICENSE.txt
snakestream-0.3.5.dist-info/METADATA
snakestream-0.3.5.dist-info/WHEEL
snakestream-0.3.5.dist-info/top_level.txt
snakestream-0.3.5.dist-info/RECORD
