Metadata-Version: 2.1
Name: snakestream
Version: 0.3.5
Summary: Java like streams for snakes
Home-page: https://github.com/carby/snakestream
Author: Tommy Derngren
Author-email: tommy.derngren@hiq.se
License: MIT
Project-URL: Documentation, https://github.com/carby/snakestream/wiki
Platform: any
Classifier: Development Status :: 4 - Beta
Classifier: Programming Language :: Python
Requires-Python: >=3.8
License-File: LICENSE.txt
Requires-Dist: importlib-metadata ; python_version < "3.8"
Provides-Extra: testing
Requires-Dist: setuptools ; extra == 'testing'
Requires-Dist: pytest ; extra == 'testing'
Requires-Dist: pytest-cov ; extra == 'testing'
Requires-Dist: pytest-asyncio ; extra == 'testing'
